cosmotool/__init__.py
cosmotool/_cosmo_bispectrum.so
cosmotool/_cosmo_cic.cpython-310-darwin.so
cosmotool/_cosmo_power.cpython-310-darwin.so
cosmotool/_cosmomath.cpython-310-darwin.so
cosmotool/_cosmotool.cpython-310-darwin.so
cosmotool/_fast_interp.cpython-310-darwin.so
cosmotool/_project.cpython-310-darwin.so
cosmotool/bispectrum.py
cosmotool/borg.py
cosmotool/cic.py
cosmotool/cl_cic.py
cosmotool/config.py
cosmotool/cosmotool.cpython-310-darwin.so
cosmotool/ctpv.py
cosmotool/fftw.py
cosmotool/grafic.py
cosmotool/simu.py
cosmotool/smooth.py
cosmotool/timing.py
cosmotool-1.3.6.dist-info/LICENCE.txt
cosmotool-1.3.6.dist-info/LICENCE_CeCILL_V2
cosmotool-1.3.6.dist-info/METADATA
cosmotool-1.3.6.dist-info/WHEEL
cosmotool-1.3.6.dist-info/top_level.txt
cosmotool-1.3.6.dist-info/RECORD
