Metadata-Version: 2.1
Name: cosmotool
Version: 1.3.6
Summary: A small cosmotool box of useful functions
License: CeCILL-v2
Keywords: cosmology,interpolation,cmake,extension
Classifier: Intended Audience :: Developers
Classifier: License :: OSI Approved :: GNU Lesser General Public License v3 (LGPLv3)
Classifier: Natural Language :: English
Classifier: Programming Language :: C
Classifier: Programming Language :: C++
Classifier: Programming Language :: Python
Classifier: Programming Language :: Python :: 3
Classifier: Programming Language :: Python :: Implementation :: CPython
Requires-Python: >=3.6
License-File: LICENCE.txt
License-File: LICENCE_CeCILL_V2
Requires-Dist: cython
Requires-Dist: numpy
Requires-Dist: cffi
Requires-Dist: numexpr
Requires-Dist: h5py
